larkspd/__init__.py
larkspd/main.py
larkspd/util.py
larkspd-1.0.2.dist-info/METADATA
larkspd-1.0.2.dist-info/WHEEL
larkspd-1.0.2.dist-info/top_level.txt
larkspd-1.0.2.dist-info/RECORD
